pec_model_master/.DS_Store
pec_model_master/__init__.py
pec_model_master/pec_pipelines/feature_engineering/WOE_encoder.py
pec_model_master/pec_pipelines/feature_engineering/__init__.py
pec_model_master/pec_pipelines/feature_engineering/generic_cleaner.py
pec_model_master/pec_pipelines/feature_engineering/utils.py
pec_model_master/pec_pipelines/model/catboost_20230618T211618.pkl
pec_model_master/pec_pipelines/preproces_pipeline.py
pec_model_master/training_model.py
pec_model_master-1.0.0.dist-info/WHEEL
pec_model_master-1.0.0.dist-info/METADATA
pec_model_master-1.0.0.dist-info/RECORD
