Metadata-Version: 2.1
Name: pec-model-master
Version: 1.0.0
Summary: 
Author: irene.casas
Author-email: irene.casas@aplazame.com
Requires-Python: >=3.9,<4.0
Classifier: Programming Language :: Python :: 3
Classifier: Programming Language :: Python :: 3.10
Classifier: Programming Language :: Python :: 3.9
Requires-Dist: catboost (==1.1.1)
Requires-Dist: category-encoders (>=2.6.1,<3.0.0)
Requires-Dist: numpy (>=1.25.0,<2.0.0)
Requires-Dist: pandas (>=2.0.2,<3.0.0)
Requires-Dist: requests (>=2.31.0,<3.0.0)
Requires-Dist: scikit-learn (>=1.2.2,<2.0.0)
